<?xml version="1.0" encoding="UTF-8"?>
<objects serializationModel="Studio.02.02.00">
	<object class="ParameterPreset" id="{e4d07879-f778-44f0-961c-e1f840b608ea}">
		<property name="name">
			<value>Random</value>
		</property>
		<relationship name="folder">
			<destination>{b4452065-5cf8-4ecb-a284-986700b5021c}</destination>
		</relationship>
		<relationship name="parameter">
			<destination>{344b9c47-dc27-42a7-b4d6-0848bb5ff1cf}</destination>
		</relationship>
	</object>
	<object class="GameParameter" id="{344b9c47-dc27-42a7-b4d6-0848bb5ff1cf}">
		<property name="maximum">
			<value>10</value>
		</property>
		<property name="initialValue">
			<value>0</value>
		</property>
	</object>
</objects>
